MANIFEST.in
README.md
setup.py
pwbmcomponents/JQuerySlider.py
pwbmcomponents/MoreInfoButton.py
pwbmcomponents/__init__.py
pwbmcomponents/_imports_.py
pwbmcomponents/bundle.js
pwbmcomponents/metadata.json
pwbmcomponents/package.json
pwbmcomponents.egg-info/PKG-INFO
pwbmcomponents.egg-info/SOURCES.txt
pwbmcomponents.egg-info/dependency_links.txt
pwbmcomponents.egg-info/top_level.txt