Metadata-Version: 1.0
Name: pwbmcomponents
Version: 1.1.0
Summary: pwbmcomponents
Home-page: UNKNOWN
Author: Nick Janetos njanetos@wharton.upenn.edu
Author-email: UNKNOWN
License: MIT
Platform: UNKNOWN
